{"updated": "2026-07-03 09:44 UTC", "bench": {"tw": 2.1, "us": -1.2}, "items": {"2330": {"price": 2445.0, "high": 2535.0, "dd": 3.6, "light": "red", "r20": 2.5, "rs": 0.4}, "2317": {"price": 240.5, "high": 314.0, "dd": 23.4, "light": "green", "r20": -17.9, "rs": -20.0}, "3260": {"price": 411.5, "high": 525.0, "dd": 21.6, "light": "green", "r20": -10.2, "rs": -12.3}, "3017": {"price": 2760.0, "high": 3010.0, "dd": 8.3, "light": "red", "r20": 1.8, "rs": -0.3}, "2327": {"price": 1045.0, "high": 1220.0, "dd": 14.3, "light": "yellow", "r20": 40.6, "rs": 38.5}, "2377": {"price": 143.0, "high": 153.5, "dd": 6.8, "light": "red", "r20": 2.1, "rs": 0.0}, "3481": {"price": 66.0, "high": 72.6, "dd": 9.1, "light": "red", "r20": 18.3, "rs": 16.2}, "2464": {"price": 172.5, "high": 206.5, "dd": 16.5, "light": "yellow", "r20": 1.5, "rs": -0.6}, "2376": {"price": 338.5, "high": 402.0, "dd": 15.8, "light": "yellow", "r20": -9.5, "rs": -11.6}, "3037": {"price": 969.0, "high": 1130.0, "dd": 14.2, "light": "yellow", "r20": -0.2, "rs": -2.3}, "2308": {"price": 2075.0, "high": 2585.0, "dd": 19.7, "light": "yellow", "r20": -14.4, "rs": -16.5}, "2382": {"price": 377.0, "high": 438.0, "dd": 13.9, "light": "yellow", "r20": -6.7, "rs": -8.8}, "3324": {"price": 1020.0, "high": 1305.0, "dd": 21.8, "light": "green", "r20": -13.9, "rs": -16.0}, "2345": {"price": 2735.0, "high": 2800.0, "dd": 2.3, "light": "red", "r20": 9.0, "rs": 6.9}, "1519": {"price": 773.0, "high": 1115.0, "dd": 30.7, "light": "green", "r20": -15.1, "rs": -17.2}, "2049": {"price": 350.0, "high": 426.0, "dd": 17.8, "light": "yellow", "r20": -2.2, "rs": -4.3}, "6188": {"price": 80.3, "high": 132.0, "dd": 39.2, "light": "green", "r20": -7.4, "rs": -9.5}, "4931": {"price": 237.5, "high": 287.0, "dd": 17.2, "light": "yellow", "r20": -8.7, "rs": -10.8}, "4967": {"price": 260.0, "high": 323.0, "dd": 19.5, "light": "yellow", "r20": -13.9, "rs": -16.0}, "3595": {"price": 2555.0, "high": 3000.0, "dd": 14.8, "light": "yellow", "r20": -4.3, "rs": -6.4}, "8027": {"price": 249.0, "high": 297.0, "dd": 16.2, "light": "yellow", "r20": -14.9, "rs": -17.0}, "2313": {"price": 229.5, "high": 305.5, "dd": 24.9, "light": "green", "r20": -13.6, "rs": -15.7}, "2383": {"price": 6080.0, "high": 6080.0, "dd": 0.0, "light": "red", "r20": 25.9, "rs": 23.8}, "6274": {"price": 1790.0, "high": 1920.0, "dd": 6.8, "light": "red", "r20": 5.6, "rs": 3.5}, "3105": {"price": 411.0, "high": 637.0, "dd": 35.5, "light": "green", "r20": -15.7, "rs": -17.8}, "8068": {"price": 19.45, "high": 29.55, "dd": 34.2, "light": "green", "r20": -3.7, "rs": -5.8}, "4971": {"price": 498.0, "high": 959.0, "dd": 48.1, "light": "green", "r20": -26.3, "rs": -28.4}, "6442": {"price": 1640.0, "high": 2540.0, "dd": 35.4, "light": "green", "r20": -23.5, "rs": -25.6}, "4979": {"price": 468.5, "high": 762.0, "dd": 38.5, "light": "green", "r20": -20.6, "rs": -22.7}, "3363": {"price": 581.0, "high": 1065.0, "dd": 45.4, "light": "green", "r20": -30.8, "rs": -32.9}, "3081": {"price": 2100.0, "high": 3305.0, "dd": 36.5, "light": "green", "r20": -18.6, "rs": -20.7}, "0050": {"price": 108.35, "high": 112.3, "dd": 3.5, "light": "red", "r20": 2.1, "rs": 0.0}, "00941": {"price": 28.64, "high": 29.8, "dd": 3.9, "light": "red", "r20": 8.4, "rs": 6.3}, "00830": {"price": 92.8, "high": 102.2, "dd": 9.2, "light": "red", "r20": -2.9, "rs": -5.0}, "00891": {"price": 37.66, "high": 39.9, "dd": 5.6, "light": "red", "r20": 4.0, "rs": 1.9}, "00911": {"price": 63.45, "high": 69.4, "dd": 8.6, "light": "red", "r20": -1.9, "rs": -4.0}, "00757": {"price": 129.1, "high": 138.1, "dd": 6.5, "light": "red", "r20": -3.4, "rs": -5.5}, "00635U": {"price": 43.6, "high": 63.0, "dd": 30.8, "light": "green", "r20": -6.8, "rs": -8.9}, "QQQ": {"price": 712.6, "high": 748.65, "dd": 4.8, "light": "red", "r20": -4.2, "rs": -3.0}, "VOO": {"price": 684.84, "high": 699.15, "dd": 2.0, "light": "red", "r20": -1.2, "rs": 0.0}, "VT": {"price": 156.17, "high": 159.41, "dd": 2.0, "light": "red", "r20": -1.1, "rs": 0.1}, "XLK": {"price": 180.59, "high": 198.73, "dd": 9.1, "light": "red", "r20": -8.0, "rs": -6.8}, "VGT": {"price": 114.64, "high": 126.0, "dd": 9.0, "light": "red", "r20": -7.5, "rs": -6.3}, "IYW": {"price": 243.48, "high": 261.01, "dd": 6.7, "light": "red", "r20": -5.5, "rs": -4.3}, "SMH": {"price": 592.29, "high": 671.83, "dd": 11.8, "light": "yellow", "r20": -7.2, "rs": -6.0}, "SOXX": {"price": 566.32, "high": 655.95, "dd": 13.7, "light": "yellow", "r20": -8.0, "rs": -6.8}, "AIQ": {"price": 61.85, "high": 70.26, "dd": 12.0, "light": "yellow", "r20": -10.6, "rs": -9.4}, "BOTZ": {"price": 37.39, "high": 41.71, "dd": 10.4, "light": "yellow", "r20": -7.2, "rs": -6.0}, "IGV": {"price": 93.57, "high": 117.99, "dd": 20.7, "light": "green", "r20": -6.6, "rs": -5.4}, "QTUM": {"price": 155.01, "high": 170.0, "dd": 8.8, "light": "red", "r20": -7.6, "rs": -6.4}, "CIBR": {"price": 90.67, "high": 94.395, "dd": 3.9, "light": "red", "r20": -1.1, "rs": 0.1}, "IAU": {"price": 77.51, "high": 104.4, "dd": 25.8, "light": "green", "r20": -7.3, "rs": -6.1}, "GLD": {"price": 378.13, "high": 509.7, "dd": 25.8, "light": "green", "r20": -7.3, "rs": -6.1}, "IBIT": {"price": 34.87, "high": 71.82, "dd": 51.4, "light": "green", "r20": -5.8, "rs": -4.6}, "SGOV": {"price": 100.44, "high": 100.74, "dd": 0.3, "light": "red", "r20": 0.0, "rs": 1.2}, "Google": {"price": 359.91, "high": 408.61, "dd": 11.9, "light": "yellow", "r20": 0.3, "rs": 1.5}, "INFQ": {"price": 12.31, "high": 21.28, "dd": 42.2, "light": "green", "r20": -29.3, "rs": -28.1}, "IONQ": {"price": 49.12, "high": 84.64, "dd": 42.0, "light": "green", "r20": -28.0, "rs": -26.8}, "RGTI": {"price": 17.94, "high": 58.15, "dd": 69.1, "light": "green", "r20": -25.5, "rs": -24.3}, "QBTS": {"price": 22.53, "high": 46.75, "dd": 51.8, "light": "green", "r20": -18.2, "rs": -17.0}}}